DataFactory/__init__.py
DataFactory/compile.py
DataFactory/sqlinterface.py
models/__init__.py
models/_int_logging.py
models/alert_providers.py
models/api.py
models/approval_rate.py
models/banks.py
models/billing_models.py
models/bins.py
models/campaign_balancer.py
models/campaigns.py
models/capfill.py
models/clients.py
models/color_index.py
models/compile.py
models/config.py
models/corp_cascade.py
models/corps.py
models/crm_errors.py
models/custom_shipping.py
models/db.py
models/discount_stats.py
models/discounter.py
models/email_reconfs.py
models/exception_log.py
models/filter_index.py
models/gateway_providers.py
models/gateways-n.py
models/gateways.py
models/hard_declines.py
models/initials.py
models/instance_data.py
models/internal_orders.py
models/invoices.py
models/iso.py
models/kk_oc_2.py
models/logga.py
models/master_campaigns.py
models/mc_promo.py
models/mids.py
models/offer_globals-b.py
models/offer_globals.py
models/offers.py
models/order_actions.py
models/order_cycles.py
models/order_processing.py
models/orders.py
models/partitioner.py
models/pixels.py
models/prices.py
models/processing_error_log.py
models/processor.py
models/processor_settings.py
models/processors.py
models/products.py
models/prospects.py
models/providers.py
models/rb_set.py
models/revenue.py
models/test_customers.py
models/test_order_verify.py
models/transactions.py
models/users.py
models/bro_clicks/__init__.py
models/bro_clicks/aff_stats.py
models/bro_clicks/alerts.py
models/bro_clicks/binrouter.py
models/bro_clicks/clicks.py
models/bro_clicks/compile.py
models/bro_clicks/conversions.py
models/bro_clicks/error_log.py
models/bro_clicks/initial_routes.py
models/bro_clicks/load_balancer-o.py
models/bro_clicks/scrub_settings.py
models/bro_clicks/splitter.py
models/bro_clicks/load_balancer/__init__.py
models/bro_clicks/load_balancer/compile.py
models/bro_clicks/load_balancer/v1.py
models/bro_clicks/load_balancer/v2.py
models/bro_clicks/load_balancer/v3.py
mg_models_occ176-10.0.3.dist-info/METADATA
mg_models_occ176-10.0.3.dist-info/WHEEL
mg_models_occ176-10.0.3.dist-info/top_level.txt
mg_models_occ176-10.0.3.dist-info/RECORD
